Metadata-Version: 2.1
Name: odoo9-addon-base-phone
Version: 9.0.0.1.0.99.dev56
Summary: Validate phone numbers
Home-page: http://www.akretion.com/
Author: Akretion,Odoo Community Association (OCA)
Author-email: support@odoo-community.org
License: AGPL-3
Platform: UNKNOWN
Classifier: Programming Language :: Python
Classifier: Framework :: Odoo
Classifier: License :: OSI Approved :: GNU Affero General Public License v3
Requires-Python: ~=2.7
Requires-Dist: odoo (<9.1a,>=9.0a)
Requires-Dist: phonenumbers
